aicloud/__init__.py
aicloud-pkg/__init__.py
aicloud_pkg/__init__.py
aicloudx/__init__.py
pkg/__init__.py
aicloudx-0.0.3.dist-info/LICENSE
aicloudx-0.0.3.dist-info/METADATA
aicloudx-0.0.3.dist-info/WHEEL
aicloudx-0.0.3.dist-info/top_level.txt
aicloudx-0.0.3.dist-info/RECORD
