Metadata-Version: 2.1
Name: aicloudx
Version: 0.0.3
Summary: 用于配合云平台进行模型训练
Home-page: https://github.com/cuidong008/aicloud
Author: cui dong
Author-email: cuidong008@126.com
License: UNKNOWN
Platform: UNKNOWN
Classifier: Programming Language :: Python :: 3
Classifier: License :: OSI Approved :: MIT License
Classifier: Operating System :: OS Independent
License-File: LICENSE
